phonecodes/__init__.py
phonecodes/phonecode_tables.py
phonecodes/phonecodes.py
phonecodes/pronlex.py
phonecodes-1.2.3.dist-info/licenses/LICENSE.txt
phonecodes-1.2.3.dist-info/METADATA
phonecodes-1.2.3.dist-info/WHEEL
phonecodes-1.2.3.dist-info/top_level.txt
phonecodes-1.2.3.dist-info/RECORD
