Metadata-Version: 2.4
Name: phonecodes
Version: 1.2.3
Summary: Tools for loading dictionaries with various phonecodes (IPA, Callhome, X-SAMPA, ARPABET, DISC=CELEX, Buckeye), for converting among those phonecodes, and for searching those dictionaries for word sequences matching a target.
License: MIT License
Project-URL: Homepage, https://github.com/ginic/phonecodes
Project-URL: Repository, https://github.com/ginic/phonecodes.git
Project-URL: Issues, https://github.com/ginic/phonecodes/issues
Project-URL: Changelog, https://github.com/ginic/phonecodes/blob/master/CHANGELOG.md
Classifier: Programming Language :: Python :: 3
Classifier: Programming Language :: Python :: 3.7
Classifier: Programming Language :: Python :: 3.8
Classifier: Programming Language :: Python :: 3.9
Classifier: Programming Language :: Python :: 3.10
Classifier: Programming Language :: Python :: 3.11
Classifier: Programming Language :: Python :: 3.12
Classifier: Programming Language :: Python :: 3.13
Classifier: Programming Language :: Python :: 3.14
Classifier: License :: OSI Approved :: MIT License
Classifier: Operating System :: OS Independent
Requires-Python: >=3.7
License-File: LICENSE.txt
Provides-Extra: test
Requires-Dist: pytest; extra == "test"
Provides-Extra: dev
Requires-Dist: ruff>=0.14.1; extra == "dev"
Dynamic: license-file
